Tabla_3_SOP/Tabla-3-SOP.v
// -----------------------------------
// Fernando José Caceros Morales (19148)
// Basado en: http://www.asic-world.com/verilog/verilog_one_day1.html#Low_level_design
// Tabla 3 SOP 
// -----------------------------------
module Tabla3SOP();	// generar y nombrar un módulo
  

wire NA,NB,NC,ND,P1,P2,P3,P4,P5,P6,P7,S1;

reg A,B,C,D;	

// podemos utilizar compuertas nativas   

not NotA (NA, A);
not NotB (NB, B);
not NotC (NC, C);
not NotD (ND, D);

and And1 (P1, NA,NB,NC,ND);
and And2 (P2, NA,NB,NC,D);
and And3 (P3, NA,NB,C,ND);
and And4 (P4, NA,NB,C,D);
and And5 (P5, A,NB,NC,ND);
and And6 (P6, A,NB,C,ND);
and And7 (P7, A,B,C,ND);

or Or1 (S1, P1,P2,P3,P4,P5,P6,P7);		

// initial sirve para definir eventos desde el tiempo t = 0

initial begin	// noten el uso del begin y end
  //monitor nos permite rastrear cambios en las entradas y salidas
  // %b = binario %d = decimal %h = hex  \t = tabulación
  $monitor("%b %b %b %b| %b", A, B, C, D, S1);
  // Declaramos valores en el tiempo 0
  A = 0;
  B = 0;
  C = 0;
  D = 0;
  
  #1 D = 1;
  #1 C = 1; D=0;
  #1 D = 1;
  #1 B=1;C=0;D=0;
  #1 D=1;
  #1 C=1;D=0;
  #1 D=1;
  #1 A=1;B=0;C=0;D=0;
  #1 D = 1;
  #1 C = 1; D=0;
  #1 D = 1;
  #1 B=1;C=0;D=0;
  #1 D=1;
  #1 C=1;D=0;
  #1 D=1;
  
  #1 $finish;   // termina la simulación
end	
initial
    begin
      $dumpfile("Tabla-3-SOP.v"); // noten que el nombre del archivo siempre es el que incluye el _tb y la extension es .vcd
      $dumpvars(0, Tabla3SOP); // noten que el nombre que está después del número 0 es el mismo que el nombre del módulo que estamos probando
    end
endmodule	//finalizar el módulo

Tabla_3_SOP/Tabla-3-SOP_tb.vcd
$date
	Fri Jul 31 23:28:58 2020
$end
$version
	Icarus Verilog
$end
$timescale
	1ps
$end
$scope module Tabla3SOP $end
$var wire 1 ! NA $end
$var wire 1 " NB $end
$var wire 1 # NC $end
$var wire 1 $ ND $end
$var wire 1 % P1 $end
$var wire 1 & P2 $end
$var wire 1 ' P3 $end
$var wire 1 ( P4 $end
$var wire 1 ) P5 $end
$var wire 1 * P6 $end
$var wire 1 + P7 $end
$var wire 1 , S1 $end
$var reg 1 - A $end
$var reg 1 . B $end
$var reg 1 / C $end
$var reg 1 0 D $end
$upscope $end
$enddefinitions $end
#0
$dumpvars
00
0/
0.
0-
1,
0+
0*
0)
0(
0'
0&
1%
1$
1#
1"
1!
$end
#1
0%
1&
0$
10
#2
1'
0&
1$
0#
00
1/
#3
0'
1(
0$
10
#4
0,
1$
0(
1#
0"
00
0/
1.
#5
0$
10
#6
1$
0#
00
1/
#7
0$
10
#8
1,
1)
1$
1#
1"
0!
00
0/
0.
1-
#9
0,
0)
0$
10
#10
1,
1*
1$
0#
00
1/
#11
0,
0*
0$
10
#12
1$
1#
0"
00
0/
1.
#13
0$
10
#14
1,
1+
1$
0#
00
1/
#15
0,
0+
0$
10
