Tabla_4_POS/Tabla-4-POS.v
// -----------------------------------
// Fernando José Caceros Morales (19148)
// Basado en: http://www.asic-world.com/verilog/verilog_one_day1.html#Low_level_design
// Tabla 4 POS 
// -----------------------------------
module Tabla4POS();	// generar y nombrar un módulo
  

wire NA,NB,NC,ND,S1,S2,S3,S4,S5,S6,S7,S8,S9,P1;

reg A,B,C,D;	

// podemos utilizar compuertas nativas   

not NotA (NA, A);
not NotB (NB, B);
not NotC (NC, C);
not NotD (ND, D);

or Or1 (S1, A,B,C,ND);
or Or2 (S2, A,NB,C,D);
or Or3 (S3, A,NB,C,ND);
or Or4 (S4, NA,B,C,ND);
or Or5 (S5, NA,B,NC,ND);
or Or6 (S6, NA,NB,C,D);
or Or7 (S7, NA,NB,C,ND);
or Or8 (S8, NA,NB,NC,D);
or Or9 (S9, NA,NB,NC,ND);

and And1 (P1, S1,S2,S3,S4,S5,S6,S7,S8,S9);		

// initial sirve para definir eventos desde el tiempo t = 0

initial begin	// noten el uso del begin y end
  //monitor nos permite rastrear cambios en las entradas y salidas
  // %b = binario %d = decimal %h = hex  \t = tabulación
  $monitor("%b %b %b %b| %b", A, B, C, D, P1);
  // Declaramos valores en el tiempo 0
  A = 0;
  B = 0;
  C = 0;
  D = 0;
  
  #1 D = 1;
  #1 C = 1; D=0;
  #1 D = 1;
  #1 B=1;C=0;D=0;
  #1 D=1;
  #1 C=1;D=0;
  #1 D=1;
  #1 A=1;B=0;C=0;D=0;
  #1 D = 1;
  #1 C = 1; D=0;
  #1 D = 1;
  #1 B=1;C=0;D=0;
  #1 D=1;
  #1 C=1;D=0;
  #1 D=1;
  
  #1 $finish;   // termina la simulación
end	
initial
    begin
      $dumpfile("Tabla-4-POS_tb.vcd"); // noten que el nombre del archivo siempre es el que incluye el _tb y la extension es .vcd
      $dumpvars(0, Tabla4POS); // noten que el nombre que está después del número 0 es el mismo que el nombre del módulo que estamos probando
    end
endmodule	//finalizar el módulo

Tabla_4_POS/Tabla-4-POS_tb.vcd
$date
	Fri Jul 31 23:29:33 2020
$end
$version
	Icarus Verilog
$end
$timescale
	1ps
$end
$scope module Tabla4POS $end
$var wire 1 ! NA $end
$var wire 1 " NB $end
$var wire 1 # NC $end
$var wire 1 $ ND $end
$var wire 1 % P1 $end
$var wire 1 & S1 $end
$var wire 1 ' S2 $end
$var wire 1 ( S3 $end
$var wire 1 ) S4 $end
$var wire 1 * S5 $end
$var wire 1 + S6 $end
$var wire 1 , S7 $end
$var wire 1 - S8 $end
$var wire 1 . S9 $end
$var reg 1 / A $end
$var reg 1 0 B $end
$var reg 1 1 C $end
$var reg 1 2 D $end
$upscope $end
$enddefinitions $end
#0
$dumpvars
02
01
00
0/
1.
1-
1,
1+
1*
1)
1(
1'
1&
1%
1$
1#
1"
1!
$end
#1
0%
0&
0$
12
#2
1%
1$
1&
0#
02
11
#3
0$
12
#4
0%
1$
1(
0'
1#
0"
02
01
10
#5
0(
1'
0$
12
#6
1%
1$
1(
0#
02
11
#7
0$
12
#8
1%
1$
1#
1*
1)
1"
0!
02
01
00
1/
#9
0%
0)
0$
12
#10
1%
1$
1)
0#
02
11
#11
0%
0*
0$
12
#12
1$
1,
0+
1#
1*
0"
02
01
10
#13
0,
1+
0$
12
#14
0-
1$
1,
0#
02
11
#15
0.
1-
0$
12
