Tabla_2_POS/Tabla-2-POS.v
// -----------------------------------
// Fernando José Caceros Morales (19148)
// Basado en: http://www.asic-world.com/verilog/verilog_one_day1.html#Low_level_design
// Tabla 2 POS 
// -----------------------------------
module Tabla2POS();	// generar y nombrar un módulo
  

wire NA,NB,NC,S1,S2,S3,S4,S5,P1;

reg A,B,C;	

// podemos utilizar compuertas nativas   

not NotA (NA, A);
not NotB (NB, B);
not NotC (NC, C);

or Or1 (S1, A,B,C);
or Or2 (S2, A,NB,C);
or Or3 (S3, A,NB,NC);
or Or4 (S4, NA,B,C);
or Or5 (S5, NA,B,NC);

and And1 (P1, S1,S2,S3,S4,S5);		

// initial sirve para definir eventos desde el tiempo t = 0

initial begin	// noten el uso del begin y end
  //monitor nos permite rastrear cambios en las entradas y salidas
  // %b = binario %d = decimal %h = hex  \t = tabulación
  $monitor("%b %b %b | %b", A, B, C, P1);
  // Declaramos valores en el tiempo 0
  A = 0;
  B = 0;
  C = 0;
  
  #1 C = 1;
  #1 B = 1; C=0;
  #1 C = 1;
  #1 A=1;B=0;C=0;
  #1 C=1;
  #1 B=1;C=0;
  #1 C=1;
  #1 $finish;   // termina la simulación
end	
initial
    begin
      $dumpfile("Tabla-2-POS_tb.vcd"); // noten que el nombre del archivo siempre es el que incluye el _tb y la extension es .vcd
      $dumpvars(0, Tabla2POS); // noten que el nombre que está después del número 0 es el mismo que el nombre del módulo que estamos probando
    end
endmodule	//finalizar el módulo

Tabla_2_POS/Tabla-2-POS_tb.vcd
$date
	Fri Jul 31 23:26:29 2020
$end
$version
	Icarus Verilog
$end
$timescale
	1ps
$end
$scope module Tabla2POS $end
$var wire 1 ! NA $end
$var wire 1 " NB $end
$var wire 1 # NC $end
$var wire 1 $ P1 $end
$var wire 1 % S1 $end
$var wire 1 & S2 $end
$var wire 1 ' S3 $end
$var wire 1 ( S4 $end
$var wire 1 ) S5 $end
$var reg 1 * A $end
$var reg 1 + B $end
$var reg 1 , C $end
$upscope $end
$enddefinitions $end
#0
$dumpvars
0,
0+
0*
1)
1(
1'
1&
0%
0$
1#
1"
1!
$end
#1
1$
1%
0#
1,
#2
0$
0&
1#
0"
0,
1+
#3
0'
1&
0#
1,
#4
1#
1)
0(
1"
1'
0!
0,
0+
1*
#5
0)
1(
0#
1,
#6
1$
1#
1)
0"
0,
1+
#7
0#
1,
